credativ_pg_migrator/__init__.py
credativ_pg_migrator/command_line.py
credativ_pg_migrator/config_parser.py
credativ_pg_migrator/constants.py
credativ_pg_migrator/database_connector.py
credativ_pg_migrator/main.py
credativ_pg_migrator/migrator_logging.py
credativ_pg_migrator/migrator_tables.py
credativ_pg_migrator/orchestrator.py
credativ_pg_migrator/planner.py
credativ_pg_migrator/connectors/__init__.py
credativ_pg_migrator/connectors/ibm_db2_connector.py
credativ_pg_migrator/connectors/informix_connector.py
credativ_pg_migrator/connectors/ms_sql_connector.py
credativ_pg_migrator/connectors/mysql_connector.py
credativ_pg_migrator/connectors/oracle_connector.py
credativ_pg_migrator/connectors/postgresql_connector.py
credativ_pg_migrator/connectors/sql_anywhere_connector.py
credativ_pg_migrator/connectors/sybase_ase_connector.py
credativ_pg_migrator-0.10.0.dist-info/licenses/AUTHORS.md
credativ_pg_migrator-0.10.0.dist-info/licenses/COPYING
credativ_pg_migrator-0.10.0.dist-info/METADATA
credativ_pg_migrator-0.10.0.dist-info/WHEEL
credativ_pg_migrator-0.10.0.dist-info/entry_points.txt
credativ_pg_migrator-0.10.0.dist-info/top_level.txt
credativ_pg_migrator-0.10.0.dist-info/RECORD
