Metadata-Version: 2.4
Name: credativ-pg-migrator
Version: 0.10.0
Summary: Migrator from proprietary and legacy databases into PostgreSQL
Home-page: https://github.com/credativ/credativ-pg-migrator.git
Author: Josef Machytka
Author-email: Josef Machytka <josef.machytka@credativ.de>
Project-URL: Homepage, https://github.com/credativ/credativ-pg-migrator
Project-URL: Issues, https://github.com/credativ/credativ-pg-migrator/issues
Classifier: Development Status :: 4 - Beta
Classifier: Environment :: Console
Classifier: Intended Audience :: System Administrators
Classifier: License :: OSI Approved :: GNU General Public License v3 or later (GPLv3+)
Classifier: Operating System :: OS Independent
Classifier: Programming Language :: Python :: 3
Classifier: Topic :: Database
Classifier: Topic :: Utilities
Requires-Python: >=3.6
License-File: COPYING
License-File: AUTHORS.md
Requires-Dist: jaydebeapi
Requires-Dist: pandas
Requires-Dist: psycopg2
Requires-Dist: pyodbc
Requires-Dist: pyyaml
Requires-Dist: sqlglot
Requires-Dist: tabulate
Dynamic: author
Dynamic: home-page
Dynamic: license-file
